__init__.py
spsam/__init__.py
spsam/get/__init__.py
spsam/get/get.py
spsam/plotting/__init__.py
spsam/plotting/_anndata.py
spsam/plotting/_scatterplots.py
spsam/plotting/palettes.py
spsam/plotting/_tools/__init__.py
spsam/preprocessing/__init__.py
spsam/preprocessing/_cycle_spot_count.py
spsam/preprocessing/_find_core_area.py
spsam/preprocessing/_get_cell_abundance.py
spsam/preprocessing/_minmaxscaler.py
spsam/preprocessing/_score_lever.py
spsam/tools/__init__.py
spsam/tools/_score_genes.py
spsam-0.0.13.dist-info/LICENSE
spsam-0.0.13.dist-info/METADATA
spsam-0.0.13.dist-info/WHEEL
spsam-0.0.13.dist-info/top_level.txt
spsam-0.0.13.dist-info/RECORD
