Metadata-Version: 2.1
Name: spsam
Version: 0.0.13
Summary: spSAM: 10X visium spot Split Align Map
Author-email: Erganzi <xxx@163.com>
Project-URL: Homepage, https://github.com/erganzi90/spsam
Project-URL: Bug Tracker, https://github.com/erganzi90/spsam/issues
Classifier: Programming Language :: Python :: 3
Classifier: License :: OSI Approved :: MIT License
Classifier: Operating System :: OS Independent
Requires-Python: >=3.9.17
License-File: LICENSE
Requires-Dist: plotly>=5.17.0
Requires-Dist: seaborn>=0.13.2
Requires-Dist: matplotlib>=3.9.3
Requires-Dist: pandas>=2.2.3
Requires-Dist: numpy>=1.26.4
Requires-Dist: scikit-learn>=1.3.0
